MANIFEST.in
README.md
setup.py
django_isitup.egg-info/PKG-INFO
django_isitup.egg-info/SOURCES.txt
django_isitup.egg-info/dependency_links.txt
django_isitup.egg-info/requires.txt
django_isitup.egg-info/top_level.txt
django_isitup.egg-info/zip-safe
isitup/__init__.py
isitup/admin.py
isitup/forms.py
isitup/models.py
isitup/signals.py
isitup/urls.py
isitup/utils.py
isitup/views.py
isitup/management/__init__.py
isitup/management/__init__.pyc
isitup/management/commands/__init__.py
isitup/management/commands/__init__.pyc
isitup/management/commands/check_services.py
isitup/management/commands/check_services.pyc
isitup/templates/isitup/base.html
isitup/templates/isitup/response_error_email.txt
isitup/templates/isitup/response_error_resolved_email.txt
isitup/templates/isitup/service_detail.html
isitup/templates/isitup/service_form.html
isitup/templates/isitup/service_list.html