Metadata-Version: 1.1
Name: django-isitup
Version: 0.1.4
Summary: A simple reusable application for managing a small orgs governance in a Django application.
Home-page: http://github.com/powellc/django-isitup
Author: Colin Powell
Author-email: colin@onecardinal.com
License: BSD
Download-URL: http://github.com/powellc/django-isitup/downloads
Platform: UNKNOWN
Classifier: Development Status :: 4 - Beta
Classifier: Environment :: Web Environment
Classifier: Intended Audience :: Developers
Classifier: License :: OSI Approved :: BSD License
Classifier: Operating System :: OS Independent
Classifier: Programming Language :: Python
Classifier: Framework :: Django
